[
  {
    "title": "Вот максимально полный хронологический список важных исторических",
    "date": "1815",
    "description": "Вот максимально полный хронологический список важных исторических событий по теме \"Внутренняя политика Александра I после 1815 года\":",
    "location": {
      "name": "Санкт-Петербург",
      "lat": 59.94,
      "lng": 30.31
    },
    "category": "Войны и сражения"
  },
  {
    "title": "Дарование конституции царству польскому** - варшава",
    "date": "1815",
    "description": "* ** 1815 ** - **Дарование Конституции Царству Польскому** - Варшава",
    "location": {
      "name": "Варшава",
      "lat": 62.82021100847557,
      "lng": 47.52430029154765
    },
    "category": "Научные достижения"
  },
  {
    "title": "Создание военных поселений** - новгородская губерния (первые",
    "date": "1815",
    "description": "* ** 1815 ** - **Создание военных поселений** - Новгородская губерния (первые поселения)",
    "location": {
      "name": "Новгородская губерния",
      "lat": 58.52,
      "lng": 31.27
    },
    "category": "Войны и сражения"
  },
  {
    "title": "Указ об освобождении крестьян эстляндской губернии** -",
    "date": "1816",
    "description": "* ** 1816 ** - **Указ об освобождении крестьян Эстляндской губернии** - Эстляндская губерния",
    "location": {
      "name": "Эстляндская губерния",
      "lat": 52.61908064008693,
      "lng": 45.930401539781
    },
    "category": "Дипломатические события"
  },
  {
    "title": "Указ об освобождении крестьян курляндской губернии** -",
    "date": "1817",
    "description": "* ** 1817 ** - **Указ об освобождении крестьян Курляндской губернии** - Курляндская губерния",
    "location": {
      "name": "Курляндская губерния",
      "lat": 62.437103962757206,
      "lng": 44.978376595437794
    },
    "category": "Научные достижения"
  },
  {
    "title": "Учреждение министерства духовных дел и народного просвещения**",
    "date": "1817",
    "description": "* ** 1817 ** - **Учреждение Министерства духовных дел и народного просвещения** - Санкт-Петербург",
    "location": {
      "name": "Санкт-Петербург",
      "lat": 59.94,
      "lng": 30.31
    },
    "category": "Экономические события"
  },
  {
    "title": "Перевод главного педагогического института в санкт-петербург и",
    "date": "1817",
    "description": "* ** 1817 ** - **Перевод Главного педагогического института в Санкт-Петербург и преобразование его в Санкт-Петербургский университет** - Санкт-Петербург",
    "location": {
      "name": "Санкт-Петербург",
      "lat": 59.94,
      "lng": 30.31
    },
    "category": "Становление государства"
  },
  {
    "title": "Речь александра i на открытии польского сейма**",
    "date": "1818",
    "description": "* ** 1818 ** - **Речь Александра I на открытии Польского сейма** - Варшава",
    "location": {
      "name": "Варшава",
      "lat": 58.88311730784346,
      "lng": 28.66973613346547
    },
    "category": "Научные достижения"
  },
  {
    "title": "Секретные общества начинают активно обсуждать проекты реформ**",
    "date": "1818",
    "description": "* ** 1818 ** - **Секретные общества начинают активно обсуждать проекты реформ** - Санкт-Петербург, Москва",
    "location": {
      "name": "Санкт-Петербург",
      "lat": 59.94,
      "lng": 30.31
    },
    "category": "Социальные реформы"
  },
  {
    "title": "Указ об освобождении крестьян лифляндской губернии** -",
    "date": "1819",
    "description": "* ** 1819 ** - **Указ об освобождении крестьян Лифляндской губернии** - Лифляндская губерния",
    "location": {
      "name": "Лифляндская губерния",
      "lat": 51.41717853102625,
      "lng": 42.6791633874306
    },
    "category": "Социальные реформы"
  },
  {
    "title": "Учреждение санкт-петербургского университета** - санкт-петербург",
    "date": "1819",
    "description": "* ** 1819 ** - **Учреждение Санкт-Петербургского университета** - Санкт-Петербург",
    "location": {
      "name": "Санкт-Петербург",
      "lat": 59.94,
      "lng": 30.31
    },
    "category": "Войны и сражения"
  },
  {
    "title": "Разгон казанского университета** - казань",
    "date": "1819",
    "description": "* ** 1819 ** - **Разгон Казанского университета** - Казань",
    "location": {
      "name": "Казань",
      "lat": 55.79,
      "lng": 49.12
    },
    "category": "Изменения границ"
  },
  {
    "title": "Волнения в семеновском полку** - санкт-петербург",
    "date": "1820",
    "description": "* ** 1820 ** - **Волнения в Семеновском полку** - Санкт-Петербург",
    "location": {
      "name": "Санкт-Петербург",
      "lat": 59.94,
      "lng": 30.31
    },
    "category": "Территориальные приобретения"
  },
  {
    "title": "Запрет на критику действий правительства в печати**",
    "date": "1820",
    "description": "* ** 1820 ** - **Запрет на критику действий правительства в печати** - Российская империя",
    "location": {
      "name": "Санкт-Петербург",
      "lat": 59.94,
      "lng": 30.31
    },
    "category": "Территориальные приобретения"
  },
  {
    "title": "Запрет деятельности масонских лож и тайных обществ**",
    "date": "1821",
    "description": "* ** 1821 ** - **Запрет деятельности масонских лож и тайных обществ** - Российская империя",
    "location": {
      "name": "Санкт-Петербург",
      "lat": 59.94,
      "lng": 30.31
    },
    "category": "Изменения границ"
  },
  {
    "title": "Указ о возобновлении права помещиков ссылать крестьян",
    "date": "1822",
    "description": "* ** 1822 ** - **Указ о возобновлении права помещиков ссылать крестьян в Сибирь** - Российская империя",
    "location": {
      "name": "Российская империя",
      "lat": 58.794685962868144,
      "lng": 34.60823530091156
    },
    "category": "Изменения границ"
  },
  {
    "title": "Указ о запрете тайных обществ и масонских",
    "date": "1822",
    "description": "* ** 1822 ** - **Указ о запрете тайных обществ и масонских лож** - Российская империя",
    "location": {
      "name": "Санкт-Петербург",
      "lat": 59.94,
      "lng": 30.31
    },
    "category": "Военные кампании"
  },
  {
    "title": "Рескрипт александра i о праве помещиков освобождать",
    "date": "1823",
    "description": "* ** 1823 ** - **Рескрипт Александра I о праве помещиков освобождать крестьян поодиночке или целыми селениями** - Российская империя",
    "location": {
      "name": "Санкт-Петербург",
      "lat": 59.94,
      "lng": 30.31
    },
    "category": "Военные кампании"
  },
  {
    "title": "Усиление цензуры в образовании и печати** -",
    "date": "1824",
    "description": "* ** 1824 ** - **Усиление цензуры в образовании и печати** - Российская империя",
    "location": {
      "name": "Санкт-Петербург",
      "lat": 59.94,
      "lng": 30.31
    },
    "category": "Становление государства"
  },
  {
    "title": "Смерть александра i** - таганрог",
    "date": "1825",
    "description": "* ** 1825 ** - **Смерть Александра I** - Таганрог",
    "location": {
      "name": "Таганрог",
      "lat": 52.605549248287566,
      "lng": 47.20820437512737
    },
    "category": "Войны и сражения"
  },
  {
    "title": "Декабря 1825 ** - **восстание декабристов** -",
    "date": "1825",
    "description": "* **14 декабря 1825 ** - **Восстание декабристов** - Санкт-Петербург, Сенатская площадь",
    "location": {
      "name": "Санкт-Петербург",
      "lat": 59.94,
      "lng": 30.31
    },
    "category": "Революции и перевороты"
  },
  {
    "title": "Этот список включает как крупные события, так",
    "date": "1815",
    "description": "Этот список включает как крупные события, так и менее известные, но важные для понимания внутренней политики Александра I после 1815 года",
    "location": {
      "name": "Санкт-Петербург",
      "lat": 59.94,
      "lng": 30.31
    },
    "category": "Военные кампании"
  },
  {
    "title": "Конечно, вот продолжение списка исторических событий, касающихся",
    "date": "1815",
    "description": "Конечно, вот продолжение списка исторических событий, касающихся внутренней политики Александра I после 1815 года, с акцентом на менее известные, но важные события:",
    "location": {
      "name": "Россия",
      "lat": 55.75,
      "lng": 37.62
    },
    "category": "Основание городов"
  },
  {
    "title": "Учреждение военных поселений** - **новгородская губерния**",
    "date": "1816",
    "description": "* ** 1816 ** - **Учреждение военных поселений** - **Новгородская губерния**",
    "location": {
      "name": "Новгородская губерния",
      "lat": 58.52,
      "lng": 31.27
    },
    "category": "Войны и сражения"
  },
  {
    "title": "Министерство духовных дел и народного просвещения** -",
    "date": "1817",
    "description": "* ** 1817 ** - **Министерство духовных дел и народного просвещения** - **Санкт-Петербург**",
    "location": {
      "name": "Санкт-Петербург",
      "lat": 59.94,
      "lng": 30.31
    },
    "category": "Революции и перевороты"
  },
  {
    "title": "Усиление цензуры и гонений на профессоров в",
    "date": "1819",
    "description": "* ** 1819 ** - **Усиление цензуры и гонений на профессоров в университетах** - **Казанский университет, Санкт-Петербургский университет и др",
    "location": {
      "name": "Казанский университет, Санкт-Петербургский университет",
      "lat": 59.94,
      "lng": 30.31
    },
    "category": "Научные достижения"
  },
  {
    "title": "Ликвидация крепостного права в прибалтике** - **эстляндия**",
    "date": "1819",
    "description": "* ** 1819 ** - **Ликвидация крепостного права в Прибалтике** - **Эстляндия**",
    "location": {
      "name": "Эстляндия",
      "lat": 49.79909380231904,
      "lng": 31.2096716991056
    },
    "category": "Становление государства"
  },
  {
    "title": "Дело\" о волнениях в лейб-гвардии семеновском полку**",
    "date": "1820",
    "description": "* ** 1820 ** - **\"Дело\" о волнениях в лейб-гвардии Семеновском полку** - **Санкт-Петербург**",
    "location": {
      "name": "Санкт-Петербург",
      "lat": 59.94,
      "lng": 30.31
    },
    "category": "Территориальные приобретения"
  },
  {
    "title": "Возобновление права помещиков ссылать крестьян в сибирь**",
    "date": "1822",
    "description": "* ** 1822 ** - **Возобновление права помещиков ссылать крестьян в Сибирь** - **Российская империя**",
    "location": {
      "name": "Российская империя",
      "lat": 64.95019556750009,
      "lng": 31.088759015920726
    },
    "category": "Восстания и бунты"
  },
  {
    "title": "Учреждение азиатского комитета** - **санкт-петербург**",
    "date": "1822",
    "description": "* ** 1822 ** - **Учреждение Азиатского комитета** - **Санкт-Петербург**",
    "location": {
      "name": "Санкт-Петербург",
      "lat": 59.94,
      "lng": 30.31
    },
    "category": "Экономические события"
  },
  {
    "title": "Указ о порядке наследования престола** - **санкт-петербург**",
    "date": "1823",
    "description": "* ** 1823 ** - **Указ о порядке наследования престола** - **Санкт-Петербург**",
    "location": {
      "name": "Санкт-Петербург",
      "lat": 59.94,
      "lng": 30.31
    },
    "category": "Становление государства"
  },
  {
    "title": "Наводнение в санкт-петербурге** - **санкт-петербург**",
    "date": "1824",
    "description": "* ** 1824 ** - **Наводнение в Санкт-Петербурге** - **Санкт-Петербург**",
    "location": {
      "name": "Санкт-Петербург",
      "lat": 59.94,
      "lng": 30.31
    },
    "category": "Социальные реформы"
  },
  {
    "title": "Ужесточение военной дисциплины и муштры в армии**",
    "date": "1825",
    "description": "* ** 1825 ** - **Ужесточение военной дисциплины и муштры в армии** - **Российская империя**",
    "location": {
      "name": "Санкт-Петербург",
      "lat": 59.94,
      "lng": 30.31
    },
    "category": "Войны и сражения"
  },
  {
    "title": "Подорожание хлеба и продовольственные волнения** - **различные",
    "date": "1825",
    "description": "* ** 1825 ** - **Подорожание хлеба и продовольственные волнения** - **Различные регионы Российской империи**",
    "location": {
      "name": "Различные регионы Российской империи",
      "lat": 47.499957884723806,
      "lng": 31.887223150158615
    },
    "category": "Войны и сражения"
  },
  {
    "title": "Смерть александра i** - **таганрог**",
    "date": "1825",
    "description": "* ** 1825 ** - **Смерть Александра I** - **Таганрог**",
    "location": {
      "name": "Таганрог",
      "lat": 45.10581346645975,
      "lng": 50.494618925571125
    },
    "category": "Восстания и бунты"
  }
]