[
  {
    "title": "Год ** - **духовная грамота князя даниила",
    "date": "1301 год",
    "description": "* ** 1301 год ** - **Духовная грамота князя Даниила Александровича** - Москва",
    "location": {
      "name": "Москва",
      "lat": 55.75,
      "lng": 37.62
    },
    "category": "Войны и сражения"
  },
  {
    "title": "Год ** - **духовная грамота ивана калиты**",
    "date": "1339 год",
    "description": "* ** 1339 год ** - **Духовная грамота Ивана Калиты** - Москва",
    "location": {
      "name": "Москва",
      "lat": 55.75,
      "lng": 37.62
    },
    "category": "Социальные реформы"
  },
  {
    "title": "Год ** - **куликовская битва** - куликово",
    "date": "1380 год",
    "description": "* ** 1380 год ** - **Куликовская битва** - Куликово поле",
    "location": {
      "name": "Куликово поле",
      "lat": 53.67,
      "lng": 38.67
    },
    "category": "Войны и сражения"
  },
  {
    "title": "Годы** - **правление ивана iii** - московское",
    "date": "1462-1505",
    "description": "* ** 1462-1505 годы** - **Правление Ивана III** - Московское государство",
    "location": {
      "name": "Москва",
      "lat": 55.75,
      "lng": 37.62
    },
    "category": "Становление государства"
  },
  {
    "title": "Год ** - **битва на реке шелони**",
    "date": "1471 год",
    "description": "* ** 1471 год ** - **Битва на реке Шелони** - Река Шелонь, Новгородская земля",
    "location": {
      "name": "Река Шелонь, Новгородская земля",
      "lat": 58.52,
      "lng": 31.27
    },
    "category": "Войны и сражения"
  },
  {
    "title": "Год ** - **стояние на реке угре**",
    "date": "1480 год",
    "description": "* ** 1480 год ** - **Стояние на реке Угре** - Река Угра",
    "location": {
      "name": "Река Угра",
      "lat": 59.67127779359644,
      "lng": 43.635900390797644
    },
    "category": "Экономические события"
  },
  {
    "title": "Год ** - **судебник ивана iii** -",
    "date": "1497 год",
    "description": "* ** 1497 год ** - **Судебник Ивана III** - Москва",
    "location": {
      "name": "Москва",
      "lat": 55.75,
      "lng": 37.62
    },
    "category": "Научные достижения"
  },
  {
    "title": "Год ** - **губная реформа** - московское",
    "date": "1535 год",
    "description": "* ** 1535 год ** - **Губная реформа** - Московское государство",
    "location": {
      "name": "Московское государство",
      "lat": 60.41777428345568,
      "lng": 37.847048929437406
    },
    "category": "Становление государства"
  },
  {
    "title": "Год ** - **первый земский собор** -",
    "date": "1549 год",
    "description": "* ** 1549 год ** - **Первый Земский собор** - Москва",
    "location": {
      "name": "Москва",
      "lat": 55.75,
      "lng": 37.62
    },
    "category": "Культура и религия"
  },
  {
    "title": "Год ** - **уложение о службе** -",
    "date": "1550 год",
    "description": "* ** 1550 год ** - **Уложение о службе** - Москва",
    "location": {
      "name": "Москва",
      "lat": 55.75,
      "lng": 37.62
    },
    "category": "Экономические события"
  },
  {
    "title": "Год ** - **создание стрелецкого войска** -",
    "date": "1550 год",
    "description": "* ** 1550 год ** - **Создание стрелецкого войска** - Москва",
    "location": {
      "name": "Москва",
      "lat": 55.75,
      "lng": 37.62
    },
    "category": "Политические реформы"
  },
  {
    "title": "Год ** - **стоглавый собор** - москва",
    "date": "1551 год",
    "description": "* ** 1551 год ** - **Стоглавый собор** - Москва",
    "location": {
      "name": "Москва",
      "lat": 55.75,
      "lng": 37.62
    },
    "category": "Культура и религия"
  },
  {
    "title": "Год ** - **отмена кормлений** - московское",
    "date": "1556 год",
    "description": "* ** 1556 год ** - **Отмена кормлений** - Московское государство",
    "location": {
      "name": "Москва",
      "lat": 55.75,
      "lng": 37.62
    },
    "category": "Становление государства"
  },
  {
    "title": "Год ** - **указ об отмене опричнины**",
    "date": "1572 год",
    "description": "* ** 1572 год ** - **Указ об отмене опричнины** - Москва",
    "location": {
      "name": "Москва",
      "lat": 55.75,
      "lng": 37.62
    },
    "category": "Экономические события"
  },
  {
    "title": "Год ** - **введение \"заповедных лет\"** -",
    "date": "1581 год",
    "description": "* ** 1581 год ** - **Введение \"заповедных лет\"** - Московское государство",
    "location": {
      "name": "Московское государство",
      "lat": 47.956979027707554,
      "lng": 39.513732386348195
    },
    "category": "Становление государства"
  },
  {
    "title": "Год ** - **указ об \"урочных летах\"**",
    "date": "1597 год",
    "description": "* ** 1597 год ** - **Указ об \"урочных летах\"** - Москва",
    "location": {
      "name": "Москва",
      "lat": 55.75,
      "lng": 37.62
    },
    "category": "Политические реформы"
  },
  {
    "title": "Крестьянское восстание под предводительством ивана болотникова",
    "date": "1606 год",
    "description": "* ** 1606 год ** - **Крестьянское восстание под предводительством Ивана Болотникова** - Юг России",
    "location": {
      "name": "Юг России",
      "lat": 64.67209928496746,
      "lng": 42.48704517502268
    },
    "category": "Революции и перевороты"
  },
  {
    "title": "Год ** - **соборное уложение** - москва",
    "date": "1649 год",
    "description": "* ** 1649 год ** - **Соборное уложение** - Москва",
    "location": {
      "name": "Москва",
      "lat": 55.75,
      "lng": 37.62
    },
    "category": "Культура и религия"
  },
  {
    "title": "Год ** - **введение подворного обложения** -",
    "date": "1679 год",
    "description": "* ** 1679 год ** - **Введение подворного обложения** - Московское государство",
    "location": {
      "name": "Московское государство",
      "lat": 49.092061058436876,
      "lng": 38.591463366832244
    },
    "category": "Становление государства"
  },
  {
    "title": "Год ** - **отмена местничества** - москва",
    "date": "1682 год",
    "description": "* ** 1682 год ** - **Отмена местничества** - Москва",
    "location": {
      "name": "Москва",
      "lat": 55.75,
      "lng": 37.62
    },
    "category": "Основание городов"
  },
  {
    "title": "Год ** - **указ о единонаследии** -",
    "date": "1714 год",
    "description": "* ** 1714 год ** - **Указ о единонаследии** - Российская империя",
    "location": {
      "name": "Санкт-Петербург",
      "lat": 59.94,
      "lng": 30.31
    },
    "category": "Основание городов"
  },
  {
    "title": "Год ** - **манифест о вольности дворянства**",
    "date": "1762 год",
    "description": "* ** 1762 год ** - **Манифест о вольности дворянства** - Российская империя",
    "location": {
      "name": "Санкт-Петербург",
      "lat": 59.94,
      "lng": 30.31
    },
    "category": "Дипломатические события"
  },
  {
    "title": "Год ** - **жалованная грамота дворянству** -",
    "date": "1785 год",
    "description": "* ** 1785 год ** - **Жалованная грамота дворянству** - Российская империя",
    "location": {
      "name": "Санкт-Петербург",
      "lat": 59.94,
      "lng": 30.31
    },
    "category": "Территориальные приобретения"
  },
  {
    "title": "Жалованная грамота ивана iii троице-сергиеву монастырю** -",
    "date": "1492",
    "description": "* [ 1492 ] - **Жалованная грамота Ивана III Троице-Сергиеву монастырю** - [Московское княжество]",
    "location": {
      "name": "Московское княжество",
      "lat": 56.667551227304024,
      "lng": 51.671879507638735
    },
    "category": "Культура и религия"
  },
  {
    "title": "Судебник 1497 года: ограничение крестьянского перехода** -",
    "date": "1497",
    "description": "* [ 1497 ] - **Судебник 1497 года: Ограничение крестьянского перехода** - [Московское княжество]",
    "location": {
      "name": "Московское княжество",
      "lat": 56.28907080829963,
      "lng": 39.88021036097258
    },
    "category": "Становление государства"
  },
  {
    "title": "Собор об еретиках (жидовствующих)** - [москва]",
    "date": "1504",
    "description": "* [ 1504 ] - **Собор об еретиках (жидовствующих)** - [Москва]",
    "location": {
      "name": "Москва",
      "lat": 55.75,
      "lng": 37.62
    },
    "category": "Культура и религия"
  },
  {
    "title": "Денежная реформа елены глинской",
    "date": "1535",
    "description": "* [ 1535 ] - **Денежная реформа Елены Глинской** - [Московское княжество]",
    "location": {
      "name": "Московское княжество",
      "lat": 45.33020578661222,
      "lng": 38.96539248253748
    },
    "category": "Становление государства"
  },
  {
    "title": "Первый земский собор** - [москва]",
    "date": "1549",
    "description": "* [ 1549 ] - **Первый Земский собор** - [Москва]",
    "location": {
      "name": "Москва",
      "lat": 55.75,
      "lng": 37.62
    },
    "category": "Культура и религия"
  },
  {
    "title": "Уложение о службе 1550 года** - [московское",
    "date": "1550",
    "description": "* [ 1550 ] - **Уложение о службе 1550 года** - [Московское княжество]",
    "location": {
      "name": "Московское княжество",
      "lat": 52.60000690349464,
      "lng": 38.928932821866084
    },
    "category": "Становление государства"
  },
  {
    "title": "Стоглавый собор** - [москва]",
    "date": "1551",
    "description": "* [ 1551 ] - **Стоглавый собор** - [Москва]",
    "location": {
      "name": "Москва",
      "lat": 55.75,
      "lng": 37.62
    },
    "category": "Культура и религия"
  },
  {
    "title": "Отмена кормлений** - [московское княжество]",
    "date": "1556",
    "description": "* [ 1556 ] - **Отмена кормлений** - [Московское княжество]",
    "location": {
      "name": "Москва",
      "lat": 55.75,
      "lng": 37.62
    },
    "category": "Становление государства"
  },
  {
    "title": "Указ об установлении \"заповедных лет\"** - [московское",
    "date": "1570",
    "description": "* [ 1570 ] - **Указ об установлении \"заповедных лет\"** - [Московское княжество]",
    "location": {
      "name": "Московское княжество",
      "lat": 52.25291151042561,
      "lng": 45.51159026480468
    },
    "category": "Становление государства"
  },
  {
    "title": "Введение \"заповедных лет\" по всей стране** -",
    "date": "1581",
    "description": "* [ 1581 ] - **Введение \"заповедных лет\" по всей стране** - [Московское княжество]",
    "location": {
      "name": "Московское княжество",
      "lat": 52.71402006552522,
      "lng": 51.961054986466166
    },
    "category": "Становление государства"
  },
  {
    "title": "Писцовые описания земель** - [московское княжество]",
    "date": "1592-1593",
    "description": "* [ 1592-1593 ] - **Писцовые описания земель** - [Московское княжество]",
    "location": {
      "name": "Московское княжество",
      "lat": 58.5640343913824,
      "lng": 50.50124094920068
    },
    "category": "Становление государства"
  },
  {
    "title": "Указ об \"урочных летах\"** - [московское княжество]",
    "date": "1597",
    "description": "* [ 1597 ] - **Указ об \"урочных летах\"** - [Московское княжество]",
    "location": {
      "name": "Москва",
      "lat": 55.75,
      "lng": 37.62
    },
    "category": "Становление государства"
  },
  {
    "title": "Великий голод** - [русское царство]",
    "date": "1601-1603",
    "description": "* [ 1601-1603 ] - **Великий голод** - [Русское царство]",
    "location": {
      "name": "Русское царство",
      "lat": 56.37359511231615,
      "lng": 44.35236423850576
    },
    "category": "Дипломатические события"
  },
  {
    "title": "Восстание ивана болотникова** - [русское царство]",
    "date": "1606-1607",
    "description": "* [ 1606-1607 ] - **Восстание Ивана Болотникова** - [Русское царство]",
    "location": {
      "name": "Тула",
      "lat": 54.19,
      "lng": 37.62
    },
    "category": "Революции и перевороты"
  },
  {
    "title": "Возвращение филарета из польского плена и усиление",
    "date": "1619",
    "description": "* [ 1619 ] - **Возвращение Филарета из польского плена и усиление его влияния** - [Русское царство]",
    "location": {
      "name": "Москва",
      "lat": 55.75,
      "lng": 37.62
    },
    "category": "Военные кампании"
  },
  {
    "title": "Соборное уложение 1649 года: окончательное закрепощение крестьян**",
    "date": "1649",
    "description": "* [ 1649 ] - **Соборное уложение 1649 года: Окончательное закрепощение крестьян** - [Русское царство]",
    "location": {
      "name": "Москва",
      "lat": 55.75,
      "lng": 37.62
    },
    "category": "Культура и религия"
  },
  {
    "title": "Введение подворного обложения** - [русское царство]",
    "date": "1679",
    "description": "* [ 1679 ] - **Введение подворного обложения** - [Русское царство]",
    "location": {
      "name": "Русское царство",
      "lat": 59.18579281703704,
      "lng": 50.3413581315648
    },
    "category": "Культура и религия"
  },
  {
    "title": "Указ о единонаследии** - [российская империя]",
    "date": "1714",
    "description": "* [ 1714 ] - **Указ о единонаследии** - [Российская империя]",
    "location": {
      "name": "Санкт-Петербург",
      "lat": 59.94,
      "lng": 30.31
    },
    "category": "Изменения границ"
  }
]