[
  {
    "title": "- смерть александра i - таганрог",
    "date": "1825",
    "description": "* **1 декабря 1825 ** - Смерть Александра I - Таганрог",
    "location": {
      "name": "Таганрог",
      "lat": 58.43928339609583,
      "lng": 38.61723158067794
    },
    "category": "Восстания и бунты"
  },
  {
    "title": "- восстание декабристов - санкт-петербург",
    "date": "1825",
    "description": "* **14 декабря 1825 ** - Восстание декабристов - Санкт-Петербург, Сенатская площадь",
    "location": {
      "name": "Санкт-Петербург",
      "lat": 59.94,
      "lng": 30.31
    },
    "category": "Революции и перевороты"
  },
  {
    "title": "Декабря 1825 ** - присяга николаю i",
    "date": "1825",
    "description": "* **14 декабря 1825 ** - Присяга Николаю I - Санкт-Петербург",
    "location": {
      "name": "Санкт-Петербург",
      "lat": 59.94,
      "lng": 30.31
    },
    "category": "Культура и религия"
  },
  {
    "title": "Июля 1826 ** - казнь декабристов -",
    "date": "1826",
    "description": "* **13 июля 1826 ** - Казнь декабристов - Санкт-Петербург, Петропавловская крепость",
    "location": {
      "name": "Санкт-Петербург",
      "lat": 59.94,
      "lng": 30.31
    },
    "category": "Становление государства"
  },
  {
    "title": "Учреждение следственной комиссии по делу декабристов -",
    "date": "1826",
    "description": "* ** 1826 ** - Учреждение Следственной комиссии по делу декабристов - Санкт-Петербург",
    "location": {
      "name": "Санкт-Петербург",
      "lat": 59.94,
      "lng": 30.31
    },
    "category": "Научные достижения"
  },
  {
    "title": "- создание iii отделения собственной его императорского величества канцелярии - санкт-петербург",
    "date": "1826",
    "description": "* ** 1826 ** - Создание III Отделения Собственной Его Императорского Величества канцелярии - Санкт-Петербург",
    "location": {
      "name": "Санкт-Петербург",
      "lat": 59.94,
      "lng": 30.31
    },
    "category": "Научные достижения"
  },
  {
    "title": "Издание \"устава о цензуре\" (\"чугунный устав\") -",
    "date": "1827",
    "description": "* ** 1827 ** - Издание \"Устава о цензуре\" (\"чугунный устав\") - Российская империя",
    "location": {
      "name": "Санкт-Петербург",
      "lat": 59.94,
      "lng": 30.31
    },
    "category": "Социальные реформы"
  },
  {
    "title": "- русско-турецкая война - балканы",
    "date": "1828-1829",
    "description": "* ** 1828-1829 ** - Русско-турецкая война - Балканы, Кавказ",
    "location": {
      "name": "Балканы",
      "lat": 59.608235799403545,
      "lng": 30.4730837405202
    },
    "category": "Войны и сражения"
  },
  {
    "title": "- польское восстание - царство польское",
    "date": "1830-1831",
    "description": "* ** 1830-1831 ** - Польское восстание - Царство Польское",
    "location": {
      "name": "Варшава",
      "lat": 63.53605157633562,
      "lng": 38.85981120757199
    },
    "category": "Революции и перевороты"
  },
  {
    "title": "Издание \"свода законов российской империи\" - российская",
    "date": "1832",
    "description": "* ** 1832 ** - Издание \"Свода законов Российской империи\" - Российская империя",
    "location": {
      "name": "Санкт-Петербург",
      "lat": 59.94,
      "lng": 30.31
    },
    "category": "Социальные реформы"
  },
  {
    "title": "Учреждение звания потомственного почетного гражданина - российская",
    "date": "1832",
    "description": "* ** 1832 ** - Учреждение звания потомственного почетного гражданина - Российская империя",
    "location": {
      "name": "Санкт-Петербург",
      "lat": 59.94,
      "lng": 30.31
    },
    "category": "Научные достижения"
  },
  {
    "title": "Формулировка \"теории официальной народности\" (уваровская триада: \"православие",
    "date": "1833",
    "description": "* ** 1833 ** - Формулировка \"Теории официальной народности\" (Уваровская триада: \"Православие, Самодержавие, Народность\") - Российская империя",
    "location": {
      "name": "Санкт-Петербург",
      "lat": 59.94,
      "lng": 30.31
    },
    "category": "Культура и религия"
  },
  {
    "title": "- открытие первой железной дороги в россии",
    "date": "1837",
    "description": "* ** 1837 ** - Открытие первой железной дороги в России (Санкт-Петербург - Царское Село) - Санкт-Петербург",
    "location": {
      "name": "Санкт-Петербург",
      "lat": 59.94,
      "lng": 30.31
    },
    "category": "Научные достижения"
  },
  {
    "title": "- денежная реформа е",
    "date": "1839-1843",
    "description": "* ** 1839-1843 ** - Денежная реформа Е",
    "location": {
      "name": "Санкт-Петербург",
      "lat": 59.94,
      "lng": 30.31
    },
    "category": "Социальные реформы"
  },
  {
    "title": "- указ об",
    "date": "1842",
    "description": "* ** 1842 ** - Указ об \"обязанных крестьянах\" - Российская империя",
    "location": {
      "name": "Российская империя",
      "lat": 47.948345865308035,
      "lng": 32.58474797282739
    },
    "category": "Дипломатические события"
  },
  {
    "title": "Строительство николаевской железной дороги (санкт-петербург - москва",
    "date": "1843-1851",
    "description": "* ** 1843-1851 ** - Строительство Николаевской железной дороги (Санкт-Петербург - Москва) - Российская империя",
    "location": {
      "name": "Санкт-Петербург - Москва",
      "lat": 55.75,
      "lng": 37.62
    },
    "category": "Территориальные приобретения"
  },
  {
    "title": "Инвентарная реформа\" в западных губерниях - западные",
    "date": "1847-1848",
    "description": "* ** 1847-1848 ** - \"Инвентарная реформа\" в Западных губерниях - Западные губернии (Белоруссия, Литва, Правобережная Украина)",
    "location": {
      "name": "Западные губернии (Белоруссия, Литва, Правобережная Украина)",
      "lat": 50.45,
      "lng": 30.52
    },
    "category": "Социальные реформы"
  },
  {
    "title": "- создание",
    "date": "1848",
    "description": "* ** 1848 ** - Создание \"Комитета 2 апреля\" - Российская империя",
    "location": {
      "name": "Санкт-Петербург",
      "lat": 59.94,
      "lng": 30.31
    },
    "category": "Изменения границ"
  },
  {
    "title": "Мрачное семилетие\" (1848-1855) - российская империя",
    "date": "1848",
    "description": "* ** 1848 ** - \"Мрачное семилетие\" (1848-1855) - Российская империя",
    "location": {
      "name": "Санкт-Петербург",
      "lat": 59.94,
      "lng": 30.31
    },
    "category": "Становление государства"
  },
  {
    "title": "Мрачное семилетие\" ( 1848-1855 ) - российская",
    "date": "1848-1855",
    "description": "* **1848** - \"Мрачное семилетие\" ( 1848-1855 ) - Российская империя",
    "location": {
      "name": "Российская империя",
      "lat": 60.613975513303956,
      "lng": 38.797235015920435
    },
    "category": "Научные достижения"
  },
  {
    "title": "Подавление венгерской революции - венгрия",
    "date": "1849",
    "description": "* ** 1849 ** - Подавление Венгерской революции - Венгрия",
    "location": {
      "name": "Венгрия",
      "lat": 60.49161084408672,
      "lng": 39.70433683421902
    },
    "category": "Революции и перевороты"
  },
  {
    "title": "- крымская война - крым",
    "date": "1853-1856",
    "description": "* ** 1853-1856 ** - Крымская война - Крым, Балтийское море, Тихий океан",
    "location": {
      "name": "Крым",
      "lat": 45.3,
      "lng": 34.2
    },
    "category": "Войны и сражения"
  },
  {
    "title": "- смерть николая i - санкт-петербург",
    "date": "1855",
    "description": "* **2 марта 1855 ** - Смерть Николая I - Санкт-Петербург",
    "location": {
      "name": "Санкт-Петербург",
      "lat": 59.94,
      "lng": 30.31
    },
    "category": "Становление государства"
  },
  {
    "title": "- восстание крестьян в черниговской губернии - черниговская губерния",
    "date": "1826",
    "description": "* ** 1826 ** - Восстание крестьян в Черниговской губернии - Черниговская губерния",
    "location": {
      "name": "Черниговская губерния",
      "lat": 50.851546302604966,
      "lng": 40.76637860361317
    },
    "category": "Революции и перевороты"
  },
  {
    "title": "- создание секретных комитетов по крестьянскому вопросу - российская империя",
    "date": "1830",
    "description": "* ** 1830 -е годы** - Создание секретных комитетов по крестьянскому вопросу - Российская империя",
    "location": {
      "name": "Санкт-Петербург",
      "lat": 59.94,
      "lng": 30.31
    },
    "category": "Военные кампании"
  },
  {
    "title": "Новый университетский устав - российская империя",
    "date": "1835",
    "description": "* ** 1835 ** - Новый университетский устав - Российская империя",
    "location": {
      "name": "Санкт-Петербург",
      "lat": 59.94,
      "lng": 30.31
    },
    "category": "Социальные реформы"
  },
  {
    "title": "Е годы** - распространение социалистических идей (кружок",
    "date": "1840",
    "description": "* ** 1840 -е годы** - Распространение социалистических идей (кружок Петрашевского) - Санкт-Петербург",
    "location": {
      "name": "Санкт-Петербург",
      "lat": 59.94,
      "lng": 30.31
    },
    "category": "Культура и религия"
  },
  {
    "title": "Е годы** - усиление борьбы с раскольниками",
    "date": "1840",
    "description": "* ** 1840 -е годы** - Усиление борьбы с раскольниками и сектантами - Российская империя",
    "location": {
      "name": "Российская империя",
      "lat": 62.464967027345565,
      "lng": 30.671328443902247
    },
    "category": "Войны и сражения"
  },
  {
    "title": "Учреждение собственной его императорского величества канцелярии (с",
    "date": "1826",
    "description": "* [ 1826 ] - **Учреждение Собственной Его Императорского Величества канцелярии (С",
    "location": {
      "name": "Санкт-Петербург",
      "lat": 59.94,
      "lng": 30.31
    },
    "category": "Научные достижения"
  },
  {
    "title": "Третье отделение, созданное в 1826 году, занималось",
    "date": "в 1826",
    "description": "Третье отделение, созданное в 1826 году, занималось политическим сыском и стало символом николаевской эпохи",
    "location": {
      "name": "Санкт-Петербург",
      "lat": 59.94,
      "lng": 30.31
    },
    "category": "Становление государства"
  },
  {
    "title": "Указ о запрете принимать крепостных крестьян в",
    "date": "1827",
    "description": "* [ 1827 ] - **Указ о запрете принимать крепостных крестьян в высшие и средние учебные заведения** - [Российская империя]",
    "location": {
      "name": "Санкт-Петербург",
      "lat": 59.94,
      "lng": 30.31
    },
    "category": "Войны и сражения"
  },
  {
    "title": "Новый цензурный устав (\"чугунный\")** - [российская империя]",
    "date": "1828",
    "description": "* [ 1828 ] - **Новый цензурный устав (\"чугунный\")** - [Российская империя]",
    "location": {
      "name": "Санкт-Петербург",
      "lat": 59.94,
      "lng": 30.31
    },
    "category": "Социальные реформы"
  },
  {
    "title": "Подавление \"холерных бунтов\"** - [различные губернии российской",
    "date": "1829",
    "description": "* [ 1829 ] - **Подавление \"холерных бунтов\"** - [Различные губернии Российской империи]",
    "location": {
      "name": "Различные губернии Российской империи",
      "lat": 61.876618009491196,
      "lng": 28.70676570979875
    },
    "category": "Революции и перевороты"
  },
  {
    "title": "Подавление польского восстания** - [царство польское]",
    "date": "1830-1831",
    "description": "* [ 1830-1831 ] - **Подавление Польского восстания** - [Царство Польское]",
    "location": {
      "name": "Царство Польское",
      "lat": 47.50078513523489,
      "lng": 41.45067508968819
    },
    "category": "Революции и перевороты"
  },
  {
    "title": "Учреждение звания потомственных почетных граждан** - [российская",
    "date": "1832",
    "description": "* [ 1832 ] - **Учреждение звания потомственных почетных граждан** - [Российская империя]",
    "location": {
      "name": "Российская империя",
      "lat": 60.50860381703592,
      "lng": 42.946910928343144
    },
    "category": "Политические реформы"
  },
  {
    "title": "Публикация \"свода законов российской империи\"** - [санкт-петербург]",
    "date": "1833",
    "description": "* [ 1833 ] - **Публикация \"Свода законов Российской империи\"** - [Санкт-Петербург]",
    "location": {
      "name": "Санкт-Петербург",
      "lat": 59.94,
      "lng": 30.31
    },
    "category": "Социальные реформы"
  },
  {
    "title": "Формулирование \"теории официальной народности\" (триада \"православие, самодержавие",
    "date": "1834",
    "description": "* [ 1834 ] - **Формулирование \"Теории официальной народности\" (триада \"Православие, Самодержавие, Народность\")** - [Санкт-Петербург]",
    "location": {
      "name": "Санкт-Петербург",
      "lat": 59.94,
      "lng": 30.31
    },
    "category": "Культура и религия"
  },
  {
    "title": "Новый университетский устав** - [российская империя]",
    "date": "1835",
    "description": "* [ 1835 ] - **Новый университетский устав** - [Российская империя]",
    "location": {
      "name": "Санкт-Петербург",
      "lat": 59.94,
      "lng": 30.31
    },
    "category": "Социальные реформы"
  },
  {
    "title": "Дело петра чаадаева и публикация \"философических писем\"**",
    "date": "1836",
    "description": "* [ 1836 ] - **Дело Петра Чаадаева и публикация \"Философических писем\"** - [Москва]",
    "location": {
      "name": "Москва",
      "lat": 55.75,
      "lng": 37.62
    },
    "category": "Социальные реформы"
  },
  {
    "title": "Реформа управления государственными крестьянами (реформа киселева)** -",
    "date": "1837-1841",
    "description": "* [ 1837-1841 ] - **Реформа управления государственными крестьянами (реформа Киселева)** - [Различные губернии Российской империи]",
    "location": {
      "name": "Различные губернии Российской империи",
      "lat": 62.51789007356106,
      "lng": 48.364540269952286
    },
    "category": "Становление государства"
  },
  {
    "title": "Указ об \"обязанных крестьянах\"** - [российская империя]",
    "date": "1842",
    "description": "* [ 1842 ] - **Указ об \"обязанных крестьянах\"** - [Российская империя]",
    "location": {
      "name": "Санкт-Петербург",
      "lat": 59.94,
      "lng": 30.31
    },
    "category": "Территориальные приобретения"
  },
  {
    "title": "Денежная реформа канкрина",
    "date": "1843",
    "description": "* [ 1843 ] - **Денежная реформа Канкрина** - [Российская империя]",
    "location": {
      "name": "Российская империя",
      "lat": 50.650346031631784,
      "lng": 50.546972673923804
    },
    "category": "Социальные реформы"
  },
  {
    "title": "Учреждение русского географического общества** - [санкт-петербург]",
    "date": "1845",
    "description": "* [ 1845 ] - **Учреждение Русского географического общества** - [Санкт-Петербург]",
    "location": {
      "name": "Санкт-Петербург",
      "lat": 59.94,
      "lng": 30.31
    },
    "category": "Войны и сражения"
  },
  {
    "title": "Подавление крестьянских волнений, вызванных \"картофельными бунтами\"** -",
    "date": "1847-1848",
    "description": "* [ 1847-1848 ] - **Подавление крестьянских волнений, вызванных \"картофельными бунтами\"** - [Различные губернии Российской империи]",
    "location": {
      "name": "Различные губернии Российской империи",
      "lat": 56.3130137186769,
      "lng": 36.133184751754946
    },
    "category": "Революции и перевороты"
  },
  {
    "title": "Мрачное семилетие\" (ужесточение цензуры и политического контроля)**",
    "date": "1848",
    "description": "* [ 1848 ] - **\"Мрачное семилетие\" (ужесточение цензуры и политического контроля)** - [Российская империя]",
    "location": {
      "name": "Санкт-Петербург",
      "lat": 59.94,
      "lng": 30.31
    },
    "category": "Социальные реформы"
  },
  {
    "title": "Период после европейских революций 1848 года, характеризовавшийся",
    "date": "1848",
    "description": "[Период после европейских революций 1848 года, характеризовавшийся усилением цензуры, политического сыска и преследования инакомыслия",
    "location": {
      "name": "Санкт-Петербург",
      "lat": 59.94,
      "lng": 30.31
    },
    "category": "Революции и перевороты"
  },
  {
    "title": "Участие в подавлении венгерской революции** - [венгрия]",
    "date": "1849",
    "description": "* [ 1849 ] - **Участие в подавлении Венгерской революции** - [Венгрия]",
    "location": {
      "name": "Венгрия",
      "lat": 51.44461490244723,
      "lng": 30.714068154320493
    },
    "category": "Революции и перевороты"
  },
  {
    "title": "Открытие николаевской железной дороги (санкт-петербург - москва)**",
    "date": "1851",
    "description": "* [ 1851 ] - **Открытие Николаевской железной дороги (Санкт-Петербург - Москва)** - [Санкт-Петербург, Москва]",
    "location": {
      "name": "Санкт-Петербург, Москва",
      "lat": 55.75,
      "lng": 37.62
    },
    "category": "Научные достижения"
  },
  {
    "title": "Крымская война** - [крымский полуостров, другие регионы]",
    "date": "1853-1856",
    "description": "* [ 1853-1856 ] - **Крымская война** - [Крымский полуостров, другие регионы]",
    "location": {
      "name": "Крымский полуостров",
      "lat": 45.3,
      "lng": 34.2
    },
    "category": "Войны и сражения"
  },
  {
    "title": "Смерть николая i** - [санкт-петербург]",
    "date": "1855",
    "description": "* [ 1855 ] - **Смерть Николая I** - [Санкт-Петербург]",
    "location": {
      "name": "Санкт-Петербург",
      "lat": 59.94,
      "lng": 30.31
    },
    "category": "Основание городов"
  }
]