[
  {
    "title": "6 ноября 1796 - смерть екатерины ii - санкт-петербург",
    "date": "1796",
    "description": "* 6 ноября 1796 - Смерть Екатерины II - Санкт-Петербург",
    "location": {
      "name": "Санкт-Петербург",
      "lat": 59.94,
      "lng": 30.31
    },
    "category": "Основание городов"
  },
  {
    "title": "6 ноября 1796 - манифест о трехдневной барщине - санкт-петербург",
    "date": "1796",
    "description": "* 6 ноября 1796 - Манифест о трехдневной барщине - Санкт-Петербург",
    "location": {
      "name": "Санкт-Петербург",
      "lat": 59.94,
      "lng": 30.31
    },
    "category": "Изменения границ"
  },
  {
    "title": "Ноябрь 1796 - освобождение из заключения политических",
    "date": "1796",
    "description": "* Ноябрь 1796 - Освобождение из заключения политических заключенных - Санкт-Петербург",
    "location": {
      "name": "Санкт-Петербург",
      "lat": 59.94,
      "lng": 30.31
    },
    "category": "Восстания и бунты"
  },
  {
    "title": "Ноябрь 1796 - возвращение из опалы а",
    "date": "1796",
    "description": "* Ноябрь 1796 - Возвращение из опалы А",
    "location": {
      "name": "Санкт-Петербург",
      "lat": 59.94,
      "lng": 30.31
    },
    "category": "Культура и религия"
  },
  {
    "title": "Декабрь 1796 - упразднение приказов и восстановление",
    "date": "1796",
    "description": "* Декабрь 1796 - Упразднение приказов и восстановление коллегий - Российская империя",
    "location": {
      "name": "Санкт-Петербург",
      "lat": 59.94,
      "lng": 30.31
    },
    "category": "Революции и перевороты"
  },
  {
    "title": "Апреля 1797 - учреждение императорской фамилии (указ",
    "date": "1797",
    "description": "* 5 апреля 1797 - Учреждение императорской фамилии (Указ о престолонаследии) - Санкт-Петербург",
    "location": {
      "name": "Санкт-Петербург",
      "lat": 59.94,
      "lng": 30.31
    },
    "category": "Основание городов"
  },
  {
    "title": "Запрет на ношение круглых шляп и фраков",
    "date": "1797",
    "description": "* 1797 - Запрет на ношение круглых шляп и фраков - Российская империя",
    "location": {
      "name": "Санкт-Петербург",
      "lat": 59.94,
      "lng": 30.31
    },
    "category": "Экономические события"
  },
  {
    "title": "1797 - указ о запрете ввоза иностранных книг и нот - российская империя",
    "date": "1797",
    "description": "* 1797 - Указ о запрете ввоза иностранных книг и нот - Российская империя",
    "location": {
      "name": "Санкт-Петербург",
      "lat": 59.94,
      "lng": 30.31
    },
    "category": "Основание городов"
  },
  {
    "title": "1797 - реформа армии по прусскому образцу - российская империя",
    "date": "1797",
    "description": "* 1797 - Реформа армии по прусскому образцу - Российская империя",
    "location": {
      "name": "Санкт-Петербург",
      "lat": 59.94,
      "lng": 30.31
    },
    "category": "Социальные реформы"
  },
  {
    "title": "Вступление россии во вторую антифранцузскую коалицию -",
    "date": "1798",
    "description": "* 1798 - Вступление России во Вторую антифранцузскую коалицию - Российская империя",
    "location": {
      "name": "Санкт-Петербург",
      "lat": 59.94,
      "lng": 30.31
    },
    "category": "Революции и перевороты"
  },
  {
    "title": "Учреждение медико-хирургической академии - санкт-петербург",
    "date": "1798",
    "description": "* 1798 - Учреждение Медико-хирургической академии - Санкт-Петербург",
    "location": {
      "name": "Санкт-Петербург",
      "lat": 59.94,
      "lng": 30.31
    },
    "category": "Научные достижения"
  },
  {
    "title": "1798 - принятие мальтийского ордена под покровительство россии - санкт-петербург",
    "date": "1798",
    "description": "* 1798 - Принятие Мальтийского ордена под покровительство России - Санкт-Петербург",
    "location": {
      "name": "Санкт-Петербург",
      "lat": 59.94,
      "lng": 30.31
    },
    "category": "Восстания и бунты"
  },
  {
    "title": "Итальянский поход суворова - северная италия",
    "date": "1799",
    "description": "* 1799 - Итальянский поход Суворова - Северная Италия",
    "location": {
      "name": "Северная Италия",
      "lat": 60.09446260166311,
      "lng": 38.87578375635719
    },
    "category": "Дипломатические события"
  },
  {
    "title": "Швейцарский поход суворова - швейцария",
    "date": "1799",
    "description": "* 1799 - Швейцарский поход Суворова - Швейцария",
    "location": {
      "name": "Швейцария",
      "lat": 63.544655082355916,
      "lng": 31.261223008804198
    },
    "category": "Военные кампании"
  },
  {
    "title": "Разрыв отношений с австрией - российская империя",
    "date": "1799",
    "description": "* 1799 - Разрыв отношений с Австрией - Российская империя",
    "location": {
      "name": "Санкт-Петербург",
      "lat": 59.94,
      "lng": 30.31
    },
    "category": "Основание городов"
  },
  {
    "title": "Сближение с наполеоном бонапартом - российская империя",
    "date": "1800",
    "description": "* 1800 - Сближение с Наполеоном Бонапартом - Российская империя",
    "location": {
      "name": "Санкт-Петербург",
      "lat": 59.94,
      "lng": 30.31
    },
    "category": "Восстания и бунты"
  },
  {
    "title": "Запрет на выезд за границу - российская",
    "date": "1800",
    "description": "* 1800 - Запрет на выезд за границу - Российская империя",
    "location": {
      "name": "Санкт-Петербург",
      "lat": 59.94,
      "lng": 30.31
    },
    "category": "Изменения границ"
  },
  {
    "title": "Подготовка к совместному франко-русскому походу в индию",
    "date": "1800",
    "description": "* 1800 - Подготовка к совместному франко-русскому походу в Индию - Российская империя",
    "location": {
      "name": "Санкт-Петербург",
      "lat": 59.94,
      "lng": 30.31
    },
    "category": "Становление государства"
  },
  {
    "title": "1800 - указ о запрете ввоза английских товаров - российская империя",
    "date": "1800",
    "description": "* 1800 - Указ о запрете ввоза английских товаров - Российская империя",
    "location": {
      "name": "Санкт-Петербург",
      "lat": 59.94,
      "lng": 30.31
    },
    "category": "Социальные реформы"
  },
  {
    "title": "Марта 1801 - заговор и убийство павла",
    "date": "1801",
    "description": "* 12 марта 1801 - Заговор и убийство Павла I - Санкт-Петербург, Михайловский замок",
    "location": {
      "name": "Санкт-Петербург",
      "lat": 59.94,
      "lng": 30.31
    },
    "category": "Изменения границ"
  },
  {
    "title": "Марта 1801 - воцарение александра i -",
    "date": "1801",
    "description": "* 12 марта 1801 - Воцарение Александра I - Санкт-Петербург",
    "location": {
      "name": "Санкт-Петербург",
      "lat": 59.94,
      "lng": 30.31
    },
    "category": "Военные кампании"
  },
  {
    "title": "Учреждение военно-сиротского дома - санкт-петербург",
    "date": "1797",
    "description": "* 1797 - Учреждение Военно-сиротского дома - Санкт-Петербург",
    "location": {
      "name": "Санкт-Петербург",
      "lat": 59.94,
      "lng": 30.31
    },
    "category": "Войны и сражения"
  },
  {
    "title": "1798 - указ о запрете вальса - российская империя",
    "date": "1798",
    "description": "* 1798 - Указ о запрете вальса - Российская империя",
    "location": {
      "name": "Санкт-Петербург",
      "lat": 59.94,
      "lng": 30.31
    },
    "category": "Политические реформы"
  },
  {
    "title": "1799 - основание города павловск - павловск",
    "date": "1799",
    "description": "* 1799 - Основание города Павловск - Павловск (под Санкт-Петербургом)",
    "location": {
      "name": "Павловск",
      "lat": 62.63261136809735,
      "lng": 38.11710805666359
    },
    "category": "Экономические события"
  },
  {
    "title": "1800 - указ о возвращении дворянам права владеть крепостными крестьянами - российская империя",
    "date": "1800",
    "description": "* 1800 - Указ о возвращении дворянам права владеть крепостными крестьянами - Российская империя",
    "location": {
      "name": "Санкт-Петербург",
      "lat": 59.94,
      "lng": 30.31
    },
    "category": "Культура и религия"
  },
  {
    "title": "1800 - указ о запрете ношения бакенбард - российская империя",
    "date": "1800",
    "description": "* 1800 - Указ о запрете ношения бакенбард - Российская империя",
    "location": {
      "name": "Санкт-Петербург",
      "lat": 59.94,
      "lng": 30.31
    },
    "category": "Научные достижения"
  },
  {
    "title": "Ноябрь] - **указ о трехдневной барщине** -",
    "date": "1796",
    "description": "[ 1796 , ноябрь] - **Указ о трехдневной барщине** - Российская империя",
    "location": {
      "name": "Российская империя",
      "lat": 48.76991038725807,
      "lng": 36.91719591981362
    },
    "category": "Политические реформы"
  },
  {
    "title": "Январь] - **учреждение департамента уделов** - российская",
    "date": "1797",
    "description": "[ 1797 , январь] - **Учреждение Департамента уделов** - Российская империя",
    "location": {
      "name": "Санкт-Петербург",
      "lat": 59.94,
      "lng": 30.31
    },
    "category": "Военные кампании"
  },
  {
    "title": "Апрель] - **указ о престолонаследии** - российская",
    "date": "1797",
    "description": "[ 1797 , апрель] - **Указ о престолонаследии** - Российская империя",
    "location": {
      "name": "Санкт-Петербург",
      "lat": 59.94,
      "lng": 30.31
    },
    "category": "Войны и сражения"
  },
  {
    "title": "Август] - **запрет на ввоз французских товаров**",
    "date": "1797",
    "description": "[ 1797 , август] - **Запрет на ввоз французских товаров** - Российская империя",
    "location": {
      "name": "Санкт-Петербург",
      "lat": 59.94,
      "lng": 30.31
    },
    "category": "Культура и религия"
  },
  {
    "title": "Ноябрь] - **учреждение медико-хирургической академии** - санкт-петербург",
    "date": "1797",
    "description": "[ 1797 , ноябрь] - **Учреждение Медико-хирургической академии** - Санкт-Петербург",
    "location": {
      "name": "Санкт-Петербург",
      "lat": 59.94,
      "lng": 30.31
    },
    "category": "Становление государства"
  },
  {
    "title": "Август] - **вступление россии во вторую антифранцузскую",
    "date": "1798",
    "description": "[ 1798 , август] - **Вступление России во Вторую антифранцузскую коалицию** - Европа",
    "location": {
      "name": "Европа",
      "lat": 50.0,
      "lng": 10.0
    },
    "category": "Политические реформы"
  },
  {
    "title": "Сентябрь] - **назначение а",
    "date": "1798",
    "description": "[ 1798 , сентябрь] - **Назначение А",
    "location": {
      "name": "Санкт-Петербург",
      "lat": 59.94,
      "lng": 30.31
    },
    "category": "Политические реформы"
  },
  {
    "title": "Апрель-август] - **итальянский поход суворова** - северная",
    "date": "1799",
    "description": "[ 1799 , апрель-август] - **Итальянский поход Суворова** - Северная Италия",
    "location": {
      "name": "Северная Италия",
      "lat": 61.81232798464225,
      "lng": 47.28674967343204
    },
    "category": "Дипломатические события"
  },
  {
    "title": "Сентябрь] - **швейцарский поход суворова** - швейцария",
    "date": "1799",
    "description": "[ 1799 , сентябрь] - **Швейцарский поход Суворова** - Швейцария",
    "location": {
      "name": "Швейцария",
      "lat": 57.32180731936093,
      "lng": 28.483120497110168
    },
    "category": "Политические реформы"
  },
  {
    "title": "Октябрь] - **разрыв россии со второй антифранцузской",
    "date": "1799",
    "description": "[ 1799 , октябрь] - **Разрыв России со Второй антифранцузской коалицией** - Европа",
    "location": {
      "name": "Санкт-Петербург",
      "lat": 59.94,
      "lng": 30.31
    },
    "category": "Восстания и бунты"
  },
  {
    "title": "Январь] - **указ о запрете ношения круглых",
    "date": "1800",
    "description": "[ 1800 , январь] - **Указ о запрете ношения круглых шляп, фраков и бакенбард** - Российская империя",
    "location": {
      "name": "Санкт-Петербург",
      "lat": 59.94,
      "lng": 30.31
    },
    "category": "Изменения границ"
  },
  {
    "title": "Декабрь] - **возобновление \"вооруженного нейтралитета\"** - санкт-петербург",
    "date": "1800",
    "description": "[ 1800 , декабрь] - **Возобновление \"Вооруженного нейтралитета\"** - Санкт-Петербург",
    "location": {
      "name": "Санкт-Петербург",
      "lat": 59.94,
      "lng": 30.31
    },
    "category": "Революции и перевороты"
  },
  {
    "title": "Январь] - **начало подготовки к индийскому походу**",
    "date": "1801",
    "description": "[ 1801 , январь] - **Начало подготовки к Индийскому походу** - Российская империя",
    "location": {
      "name": "Санкт-Петербург",
      "lat": 59.94,
      "lng": 30.31
    },
    "category": "Военные кампании"
  },
  {
    "title": "Февраль] - **запрет на выезд за границу**",
    "date": "1801",
    "description": "[ 1801 , февраль] - **Запрет на выезд за границу** - Российская империя",
    "location": {
      "name": "Санкт-Петербург",
      "lat": 59.94,
      "lng": 30.31
    },
    "category": "Изменения границ"
  },
  {
    "title": "Дворцовый переворот и убийство павла i",
    "date": "1801",
    "description": "[ 1801 , март] - **Дворцовый переворот и убийство Павла I** - Санкт-Петербург, Михайловский замок",
    "location": {
      "name": "Санкт-Петербург, Михайловский замок",
      "lat": 59.94,
      "lng": 30.31
    },
    "category": "Революции и перевороты"
  }
]