[
  {
    "title": "- смерть василия ii тёмного - москва",
    "date": "1462",
    "description": "[ 1462 , 27 октября] - Смерть Василия II Тёмного - Москва",
    "location": {
      "name": "Москва (Кремль)",
      "lat": 55.75,
      "lng": 37.62
    },
    "category": "Изменения границ"
  },
  {
    "title": "Захват новгорода великим князем московским - новгород",
    "date": "1472",
    "description": "[ 1472 ] - Захват Новгорода Великим князем Московским - Новгород",
    "location": {
      "name": "Новгород",
      "lat": 58.52,
      "lng": 31.27
    },
    "category": "Социальные реформы"
  },
  {
    "title": "Присоединение твери к московскому княжеству - тверь",
    "date": "1478",
    "description": "[ 1478 ] - Присоединение Твери к Московскому княжеству - Тверь",
    "location": {
      "name": "Тверь",
      "lat": 55.09074702082326,
      "lng": 30.009974612489323
    },
    "category": "Становление государства"
  },
  {
    "title": "Августа] - ставка на угре - угра",
    "date": "1480",
    "description": "[ 1480 , 11 августа] - Ставка на Угре - Угра (река)",
    "location": {
      "name": "Ставка на Угре (река Угра, близ села Угра в Калужской области)",
      "lat": 59.22765367397318,
      "lng": 50.56792506387471
    },
    "category": "Восстания и бунты"
  },
  {
    "title": "Присоединение ярославля к московскому княжеству - ярославль",
    "date": "1485",
    "description": "[ 1485 ] - Присоединение Ярославля к Московскому княжеству - Ярославль",
    "location": {
      "name": "Ярославль",
      "lat": 57.63,
      "lng": 39.87
    },
    "category": "Становление государства"
  },
  {
    "title": "Присоединение вятки к московскому княжеству - вятка",
    "date": "1489",
    "description": "[ 1489 ] - Присоединение Вятки к Московскому княжеству - Вятка",
    "location": {
      "name": "Вятка (Вятская земля)",
      "lat": 55.40867802423237,
      "lng": 32.18532518951211
    },
    "category": "Становление государства"
  },
  {
    "title": "Присоединение пскова к московскому княжеству - псков",
    "date": "1493",
    "description": "[ 1493 ] - Присоединение Пскова к Московскому княжеству - Псков",
    "location": {
      "name": "Псков",
      "lat": 57.82,
      "lng": 28.33
    },
    "category": "Становление государства"
  },
  {
    "title": "Корреспонденция с императором максимилианом i - москва",
    "date": "1497",
    "description": "[ 1497 ] - Корреспонденция с императором Максимилианом I - Москва",
    "location": {
      "name": "Москва",
      "lat": 55.75,
      "lng": 37.62
    },
    "category": "Научные достижения"
  },
  {
    "title": "Присоединение ростова великого к московскому княжеству -",
    "date": "1500",
    "description": "[ 1500 ] - Присоединение Ростова Великого к Московскому княжеству - Ростов Великий",
    "location": {
      "name": "Ростов Великий",
      "lat": 57.401442506549145,
      "lng": 30.509014983911356
    },
    "category": "Становление государства"
  },
  {
    "title": "Присоединение мурома к московскому княжеству - муром",
    "date": "1503",
    "description": "[ 1503 ] - Присоединение Мурома к Московскому княжеству - Муром",
    "location": {
      "name": "Муром",
      "lat": 60.34024049322554,
      "lng": 31.334611778837214
    },
    "category": "Становление государства"
  },
  {
    "title": "- смерть ивана iii - москва",
    "date": "1510",
    "description": "[ 1510 , 22 октября] - Смерть Ивана III - Москва",
    "location": {
      "name": "Москва, Кремль (предполагается, что Иван III умер в своём дворце в Московском Кремле)",
      "lat": 55.75,
      "lng": 37.62
    },
    "category": "Культура и религия"
  }
]